<?xml version="1.0"?>
<PostInfo>
    <PostsInfoRow>
        <PostData
            Id="41"
            PublishDate="2017-01-01 18:18:45"
            Author="admin"
            ModifiedDate="2017-01-01 18:18:45"
        >
            <PostTitle>याद रहेगी</PostTitle>
        </PostData>
        <PostContent><![CDATA[दिल में आपकी हर याद रहेगी<br />
<br />
बस्ती छोटी है मगर आबाद रहेगी<br />
<br />
चाहे हम भुला दे ज़माने को<br />
<br />
पर अप्प्ली ये प्यारी से बात हमेशा याद रहेगी]]></PostContent>
        <PostMetaData>
            <PostMetaDataRow
                PostId="41"
                MetaKey="ratings_users"
                MetaValue="1"
            >
            </PostMetaDataRow>
            <PostMetaDataRow
                PostId="41"
                MetaKey="ratings_score"
                MetaValue="5"
            >
            </PostMetaDataRow>
            <PostMetaDataRow
                PostId="41"
                MetaKey="ratings_average"
                MetaValue="5"
            >
            </PostMetaDataRow>
        </PostMetaData><CommentsData>
    </CommentsData><TermsData>
        <TermsDataRow
            PostId="41"
            Taxonomy="category"
        >
            <TermName>Gen Shayari</TermName>

        </TermsDataRow>
    </TermsData></PostsInfoRow>
    <PostsInfoRow>
        <PostData
            Id="40"
            PublishDate="2017-01-01 18:17:38"
            Author="admin"
            ModifiedDate="2017-01-01 18:17:38"
        >
            <PostTitle>दिल मैं जगह</PostTitle>
        </PostData>
        <PostContent><![CDATA[तोड़ दो वो कसम जो खायी है<br />
<br />
कभी कभी याद कर लेने में क्या बुराई है<br />
<br />
याद अओको किये बिना रहा भी तो नहीं जाता<br />
<br />
दिल मैं जगह अपने ऐसी जो बनायीं है ...]]></PostContent>
        <PostMetaData>
            <PostMetaDataRow
                PostId="40"
                MetaKey="ratings_users"
                MetaValue="1"
            >
            </PostMetaDataRow>
            <PostMetaDataRow
                PostId="40"
                MetaKey="ratings_score"
                MetaValue="5"
            >
            </PostMetaDataRow>
            <PostMetaDataRow
                PostId="40"
                MetaKey="ratings_average"
                MetaValue="5"
            >
            </PostMetaDataRow>
        </PostMetaData><CommentsData>
    </CommentsData><TermsData>
        <TermsDataRow
            PostId="40"
            Taxonomy="category"
        >
            <TermName>Gen Shayari</TermName>

        </TermsDataRow>
    </TermsData></PostsInfoRow>
    <PostsInfoRow>
        <PostData
            Id="39"
            PublishDate="2017-01-01 18:15:46"
            Author="admin"
            ModifiedDate="2017-01-01 18:15:46"
        >
            <PostTitle>फीवर मोहब्बत का</PostTitle>
        </PostData>
        <PostContent><![CDATA[हसीनों से मिलें नज़रें अट्रैक्शन हो भी सकता है,<br />
<br />
चढ़े फीवर मोहब्बत का तो एक्शन हो भी सकता है,<br />
<br />
हसीनों को मुसीबत तुम समझ कर दूर ही रहना,<br />
<br />
ये अंग्रेजी दवाएं हैं रिएक्शन हो भी सकता है..!!<br />
<br />
<strong></strong>💥☺😜😎💥🙏😀🙏]]></PostContent>
        <PostMetaData>
            <PostMetaDataRow
                PostId="39"
                MetaKey="ratings_users"
                MetaValue="1"
            >
            </PostMetaDataRow>
            <PostMetaDataRow
                PostId="39"
                MetaKey="ratings_score"
                MetaValue="5"
            >
            </PostMetaDataRow>
            <PostMetaDataRow
                PostId="39"
                MetaKey="ratings_average"
                MetaValue="5"
            >
            </PostMetaDataRow>
        </PostMetaData><CommentsData>
    </CommentsData><TermsData>
        <TermsDataRow
            PostId="39"
            Taxonomy="category"
        >
            <TermName>Gen Shayari</TermName>

        </TermsDataRow>
    </TermsData></PostsInfoRow>
    <PostsInfoRow>
        <PostData
            Id="24"
            PublishDate="2017-01-01 18:10:14"
            Author="admin"
            ModifiedDate="2017-01-01 18:10:14"
        >
            <PostTitle>तुम सा प्यारा</PostTitle>
        </PostData>
        <PostContent><![CDATA[हसना हमारा किसी को गवारा नहीं होता ....<br />
<br />
हर मुसाफिर जिंदिगी का सहारा नहीं होता ....<br />
<br />
मिलते है बहुत लोग इस तनहा ज़िन्दगी में  ....<br />
<br />
पर कोई दोस्त तुम सा प्यारा नहीं होता ....]]></PostContent>
        <PostMetaData>
            <PostMetaDataRow
                PostId="24"
                MetaKey="ratings_users"
                MetaValue="1"
            >
            </PostMetaDataRow>
            <PostMetaDataRow
                PostId="24"
                MetaKey="ratings_score"
                MetaValue="5"
            >
            </PostMetaDataRow>
            <PostMetaDataRow
                PostId="24"
                MetaKey="ratings_average"
                MetaValue="5"
            >
            </PostMetaDataRow>
        </PostMetaData><CommentsData>
    </CommentsData><TermsData>
        <TermsDataRow
            PostId="24"
            Taxonomy="category"
        >
            <TermName>Gen Shayari</TermName>

        </TermsDataRow>
    </TermsData></PostsInfoRow>
    <PostsInfoRow>
        <PostData
            Id="23"
            PublishDate="2017-01-01 18:08:42"
            Author="admin"
            ModifiedDate="2017-01-01 18:08:42"
        >
            <PostTitle>भूल को भुला देना</PostTitle>
        </PostData>
        <PostContent><![CDATA[भूल से कोई भूल हुई तो भूल समझ के भुला देना<br />
<br />
अरे भुलाना सिर्फ भूक को ऐ ज़ालिम ...<br />
<br />
कहीं भूल से भी हमें न भुला देना...]]></PostContent>
        <PostMetaData>
            <PostMetaDataRow
                PostId="23"
                MetaKey="ratings_users"
                MetaValue="1"
            >
            </PostMetaDataRow>
            <PostMetaDataRow
                PostId="23"
                MetaKey="ratings_score"
                MetaValue="5"
            >
            </PostMetaDataRow>
            <PostMetaDataRow
                PostId="23"
                MetaKey="ratings_average"
                MetaValue="5"
            >
            </PostMetaDataRow>
        </PostMetaData><CommentsData>
    </CommentsData><TermsData>
        <TermsDataRow
            PostId="23"
            Taxonomy="category"
        >
            <TermName>Gen Shayari</TermName>

        </TermsDataRow>
    </TermsData></PostsInfoRow>
    <PostsInfoRow>
        <PostData
            Id="22"
            PublishDate="2017-01-01 18:06:57"
            Author="admin"
            ModifiedDate="2017-01-01 18:06:57"
        >
            <PostTitle>धोखेबाज़ सनम</PostTitle>
        </PostData>
        <PostContent><![CDATA[लोग इश्क करते है बड़े शोर के साथ ...<br />
<br />
हमने भी किया बड़े जोर के साथ ...<br />
<br />
मगर अब करेंगे थोडा गौर के साथ ...<br />
<br />
क्यूँ की कल उसको देखा किसी और के साथ ...]]></PostContent>
        <PostMetaData>
            <PostMetaDataRow
                PostId="22"
                MetaKey="ratings_users"
                MetaValue="1"
            >
            </PostMetaDataRow>
            <PostMetaDataRow
                PostId="22"
                MetaKey="ratings_score"
                MetaValue="5"
            >
            </PostMetaDataRow>
            <PostMetaDataRow
                PostId="22"
                MetaKey="ratings_average"
                MetaValue="5"
            >
            </PostMetaDataRow>
        </PostMetaData><CommentsData>
    </CommentsData><TermsData>
        <TermsDataRow
            PostId="22"
            Taxonomy="category"
        >
            <TermName>Gen Shayari</TermName>

        </TermsDataRow>
    </TermsData></PostsInfoRow>
    <PostsInfoRow>
        <PostData
            Id="21"
            PublishDate="2017-01-01 18:05:24"
            Author="admin"
            ModifiedDate="2017-01-01 18:20:01"
        >
            <PostTitle>वो कसम दे गए</PostTitle>
        </PostData>
        <PostContent><![CDATA[दर्द दे गए सितम भी दे गए;<br />
<br />
ज़ख़्म के साथ वो मरहम भी दे गए;<br />
<br />
दो लफ़्ज़ों से कर गए अपना मन हल्का;<br />
<br />
और हमें कभी ना रोने की कसम दे गए।]]></PostContent>
        <PostMetaData>
            <PostMetaDataRow
                PostId="21"
                MetaKey="ratings_users"
                MetaValue="1"
            >
            </PostMetaDataRow>
            <PostMetaDataRow
                PostId="21"
                MetaKey="ratings_score"
                MetaValue="5"
            >
            </PostMetaDataRow>
            <PostMetaDataRow
                PostId="21"
                MetaKey="ratings_average"
                MetaValue="5"
            >
            </PostMetaDataRow>
        </PostMetaData><CommentsData>
    </CommentsData><TermsData>
        <TermsDataRow
            PostId="21"
            Taxonomy="category"
        >
            <TermName>Gen Shayari</TermName>

        </TermsDataRow>
        <TermsDataRow
            PostId="21"
            Taxonomy="category"
        >
            <TermName>Love Shayari</TermName>

        </TermsDataRow>
    </TermsData></PostsInfoRow>
    <PostsInfoRow>
        <PostData
            Id="20"
            PublishDate="2017-01-01 18:04:51"
            Author="admin"
            ModifiedDate="2017-01-01 18:21:10"
        >
            <PostTitle>आप की एक नज़र</PostTitle>
        </PostData>
        <PostContent><![CDATA[इश्क ने हमें बेनाम कर दिया...<br />
<br />
हर ख़ुशी से हमें अनजान कर दिया...<br />
<br />
हमने तो कभी नहीं चाहा के हमें भी मोहब्बत हो ...<br />
<br />
लेकिन आप की एक नज़र ने हमें नीलाम कर दिया ...]]></PostContent>
        <PostMetaData>
            <PostMetaDataRow
                PostId="20"
                MetaKey="ratings_users"
                MetaValue="1"
            >
            </PostMetaDataRow>
            <PostMetaDataRow
                PostId="20"
                MetaKey="ratings_score"
                MetaValue="5"
            >
            </PostMetaDataRow>
            <PostMetaDataRow
                PostId="20"
                MetaKey="ratings_average"
                MetaValue="5"
            >
            </PostMetaDataRow>
        </PostMetaData><CommentsData>
    </CommentsData><TermsData>
        <TermsDataRow
            PostId="20"
            Taxonomy="category"
        >
            <TermName>Gen Shayari</TermName>

        </TermsDataRow>
        <TermsDataRow
            PostId="20"
            Taxonomy="category"
        >
            <TermName>Love Shayari</TermName>

        </TermsDataRow>
    </TermsData></PostsInfoRow>
    <PostsInfoRow>
        <PostData
            Id="19"
            PublishDate="2017-01-01 18:03:20"
            Author="admin"
            ModifiedDate="2017-01-01 18:21:21"
        >
            <PostTitle>क्या प्यार ऐसा ही होता हैं</PostTitle>
        </PostData>
        <PostContent><![CDATA[चला गया वो कुछ इस तरह ….<br />
जैसे वो कभी मेरा था ही नहीं !!<br />
<br />
मुझे ज़िंदा तो रखा उसने…<br />
मगर मुझ मैं अब मैं ही नहीं !!<br />
<br />
क्या प्यार ऐसा ही होता हैं …!!<br />
<br />
दिल तो छोड़ गया धड़कने के लिए ..<br />
मगर अब कोई जज्बात ही नहीं !!]]></PostContent>
        <PostMetaData>
            <PostMetaDataRow
                PostId="19"
                MetaKey="ratings_users"
                MetaValue="1"
            >
            </PostMetaDataRow>
            <PostMetaDataRow
                PostId="19"
                MetaKey="ratings_score"
                MetaValue="5"
            >
            </PostMetaDataRow>
            <PostMetaDataRow
                PostId="19"
                MetaKey="ratings_average"
                MetaValue="5"
            >
            </PostMetaDataRow>
        </PostMetaData><CommentsData>
    </CommentsData><TermsData>
        <TermsDataRow
            PostId="19"
            Taxonomy="category"
        >
            <TermName>Gen Shayari</TermName>

        </TermsDataRow>
        <TermsDataRow
            PostId="19"
            Taxonomy="category"
        >
            <TermName>Love Shayari</TermName>

        </TermsDataRow>
    </TermsData></PostsInfoRow>
    <PostsInfoRow>
        <PostData
            Id="18"
            PublishDate="2017-01-01 18:02:06"
            Author="admin"
            ModifiedDate="2017-01-01 18:02:06"
        >
            <PostTitle>इंतज़ार शायरी</PostTitle>
        </PostData>
        <PostContent><![CDATA[जिंदगी के सफर का सीलसिला,<br />
<br />
कोइ मिल गया कोइ बिछड़ गया,<br />
<br />
जिन्हे माँगा था दिन रात दुआ ओ मे,<br />
<br />
वो बिना मांगे किसी और को मिल गया...]]></PostContent>
        <PostMetaData>
            <PostMetaDataRow
                PostId="18"
                MetaKey="ratings_users"
                MetaValue="1"
            >
            </PostMetaDataRow>
            <PostMetaDataRow
                PostId="18"
                MetaKey="ratings_score"
                MetaValue="5"
            >
            </PostMetaDataRow>
            <PostMetaDataRow
                PostId="18"
                MetaKey="ratings_average"
                MetaValue="5"
            >
            </PostMetaDataRow>
        </PostMetaData><CommentsData>
    </CommentsData><TermsData>
        <TermsDataRow
            PostId="18"
            Taxonomy="category"
        >
            <TermName>Gen Shayari</TermName>

        </TermsDataRow>
    </TermsData></PostsInfoRow>
    <PostsInfoRow>
        <PostData
            Id="15"
            PublishDate="2016-12-31 15:35:06"
            Author="admin"
            ModifiedDate="2017-01-01 18:20:53"
        >
            <PostTitle>मेरी यादो मे तुम हो</PostTitle>
        </PostData>
        <PostContent><![CDATA[मेरी यादो मे तुम हो,<br />
या मुझ मे ही तुम हो,<br />
<br />
मेरे खयालो मे तुम हो,<br />
या मेरा खयाल ही तुम हो,<br />
<br />
दिल मेरा धडक के पूछे, बार बार एक ही बात...<br />
मेरी जान मे तुम हो,<br />
या मेरी जान ही तुम हो…!!<br />
<br />
मोहब्बत‬ यू ही ‪किसी‬ से ‎हुवा‬ नही ‪करती‬....... ‪<br />
अपना‬ वजुद ‪भुलना‬ पडता ‪‎हे‬ किसी ‪‎को‬ अपना बनाने के लिए]]></PostContent>
        <PostMetaData>
            <PostMetaDataRow
                PostId="15"
                MetaKey="ratings_users"
                MetaValue="1"
            >
            </PostMetaDataRow>
            <PostMetaDataRow
                PostId="15"
                MetaKey="ratings_score"
                MetaValue="5"
            >
            </PostMetaDataRow>
            <PostMetaDataRow
                PostId="15"
                MetaKey="ratings_average"
                MetaValue="5"
            >
            </PostMetaDataRow>
        </PostMetaData><CommentsData>
    </CommentsData><TermsData>
        <TermsDataRow
            PostId="15"
            Taxonomy="category"
        >
            <TermName>Gen Shayari</TermName>

        </TermsDataRow>
        <TermsDataRow
            PostId="15"
            Taxonomy="category"
        >
            <TermName>Love Shayari</TermName>

        </TermsDataRow>
    </TermsData></PostsInfoRow>
</PostInfo>